Workbook

Sheet Cover
A1: Starbucks Corporation Financial Model
A2: Навчальна базова фінансова модель за даними реального підприємства
A4: Компанія | B4: Starbucks Corporation
A5: Тікер | B5: SBUX
A6: Галузь | B6: Ресторани / спеціалізована кавова роздрібна торгівля
A7: Валюта та одиниці | B7: USD millions
A8: Історичний період | B8: FY2023-FY2025
A9: Прогнозний період | B9: FY2026E-FY2028E
A10: Основне джерело | B10: Starbucks Fiscal 2025 Annual Report, Form 10-K
A11: Статус моделі | B11: =Checks!F10
A14: Коротка логіка
A15: Модель бере фактичні фінансові дані Starbucks за 2023-2025 роки, додає припущення для 2026-2028 років, формує спрощений P&L, рахує break-even revenue та показує чутливість прибутку до Revenue growth і Variable cost ratio.

Sheet Data
A1: Historical Data
A2: Actuals from Starbucks Fiscal 2025 Annual Report, USD millions
A3: Metric | B3: 2023A | C3: 2024A | D3: 2025A | E3: Source ID | F3: Notes
A4: Revenue | B4: 35975.6 | C4: 36176.2 | D4: 37184.4 | E4: S1 | F4: Form 10-K consolidated results of operations
A5: Product and distribution costs | B5: 11409.1 | C5: 11180.6 | D5: 11658.2 | E5: S1 | F5: Form 10-K consolidated results of operations
A6: Store operating expenses | B6: 14720.3 | C6: 15286.5 | D6: 17058.9 | E6: S1 | F6: Form 10-K consolidated results of operations
A7: Other operating expenses | B7: 539.4 | C7: 565.6 | D7: 584.6 | E7: S1 | F7: Form 10-K consolidated results of operations
A8: Depreciation and amortization | B8: 1362.6 | C8: 1512.6 | D8: 1684.7 | E8: S1 | F8: Form 10-K consolidated results of operations
A9: General and administrative expenses | B9: 2441.3 | C9: 2523.3 | D9: 2617.2 | E9: S1 | F9: Form 10-K consolidated results of operations
A10: Restructuring and impairments | B10: 21.8 | C10: 0 | D10: 892 | E10: S1 | F10: Form 10-K consolidated results of operations
A11: Total operating expenses | B11: =SUM(B5:B10) | C11: =SUM(C5:C10) | D11: =SUM(D5:D10) | E11: S1 | F11: Form 10-K consolidated results of operations
A12: Income from equity investees | B12: 298.4 | C12: 301.2 | D12: 247.8 | E12: S1 | F12: Form 10-K consolidated results of operations
A13: Operating income | B13: =B4-B11+B12 | C13: =C4-C11+C12 | D13: =D4-D11+D12 | E13: S1 | F13: Form 10-K consolidated results of operations
A14: Operating margin | B14: =B13/B4 | C14: =C13/C4 | D14: =D13/D4 | E14: S1 | F14: Form 10-K consolidated results of operations
A15: Net earnings attributable to Starbucks | B15: 4124.5 | C15: 3760.9 | D15: 1856.4 | E15: S1 | F15: Form 10-K consolidated results of operations

Sheet Assumptions
A1: Assumptions
A2: Blue/yellow cells are editable assumptions
A3: Driver | B3: 2026E | C3: 2027E | D3: 2028E | E3: Rationale
A4: Revenue growth | B4: 0.035 | C4: 0.04 | D4: 0.04 | E4: Moderate recovery after FY2025; conservative normalized growth.
A5: Variable cost ratio | B5: 0.765 | C5: 0.76 | D5: 0.755 | E5: Costs tied to revenue: product, distribution, store, and other operating costs.
A6: Product/distribution share of variable costs | B6: 0.385 | C6: 0.385 | D6: 0.385 | E6: Approximate split based on FY2025 cost structure.
A7: Store operating share of variable costs | B7: 0.595 | C7: 0.595 | D7: 0.595 | E7: Main variable/semi-variable operating cost block.
A8: Other operating share of variable costs | B8: 0.02 | C8: 0.02 | D8: 0.02 | E8: Small remaining operating cost category.
A9: Fixed cost growth | B9: 0.03 | C9: 0.03 | D9: 0.03 | E9: D&A and G&A grow below revenue growth.
A10: Equity income as % of revenue | B10: 0.006 | C10: 0.006 | D10: 0.006 | E10: Based on recent historical range.
A11: Restructuring costs | B11: 300 | C11: 100 | D11: 50 | E11: Assumed decline after elevated FY2025 restructuring costs.
A14: Convention
A15: Forecast formulas reference these assumptions. Change blue/yellow cells to test another scenario.

Sheet P&L
A1: Simplified P&L
A2: Historical actuals and forecast, USD millions
A3: Metric | B3: 2023A | C3: 2024A | D3: 2025A | E3: 2026E | F3: 2027E | G3: 2028E
A4: Revenue | B4: =Data!B4 | C4: =Data!C4 | D4: =Data!D4 | E4: =D4*(1+Assumptions!B$4) | F4: =E4*(1+Assumptions!C$4) | G4: =F4*(1+Assumptions!D$4)
A5: Product and distribution costs | B5: =Data!B5 | C5: =Data!C5 | D5: =Data!D5 | E5: =E4*Assumptions!B$5*Assumptions!B$6 | F5: =F4*Assumptions!C$5*Assumptions!C$6 | G5: =G4*Assumptions!D$5*Assumptions!D$6
A6: Store operating expenses | B6: =Data!B6 | C6: =Data!C6 | D6: =Data!D6 | E6: =E4*Assumptions!B$5*Assumptions!B$7 | F6: =F4*Assumptions!C$5*Assumptions!C$7 | G6: =G4*Assumptions!D$5*Assumptions!D$7
A7: Other operating expenses | B7: =Data!B7 | C7: =Data!C7 | D7: =Data!D7 | E7: =E4*Assumptions!B$5*Assumptions!B$8 | F7: =F4*Assumptions!C$5*Assumptions!C$8 | G7: =G4*Assumptions!D$5*Assumptions!D$8
A8: Depreciation and amortization | B8: =Data!B8 | C8: =Data!C8 | D8: =Data!D8 | E8: =D8*(1+Assumptions!B$9) | F8: =E8*(1+Assumptions!C$9) | G8: =F8*(1+Assumptions!D$9)
A9: General and administrative expenses | B9: =Data!B9 | C9: =Data!C9 | D9: =Data!D9 | E9: =D9*(1+Assumptions!B$9) | F9: =E9*(1+Assumptions!C$9) | G9: =F9*(1+Assumptions!D$9)
A10: Restructuring and impairments | B10: =Data!B10 | C10: =Data!C10 | D10: =Data!D10 | E10: =Assumptions!B$11 | F10: =Assumptions!C$11 | G10: =Assumptions!D$11
A11: Total operating expenses | B11: =Data!B11 | C11: =Data!C11 | D11: =Data!D11 | E11: =SUM(E5:E10) | F11: =SUM(F5:F10) | G11: =SUM(G5:G10)
A12: Income from equity investees | B12: =Data!B12 | C12: =Data!C12 | D12: =Data!D12 | E12: =E4*Assumptions!B$10 | F12: =F4*Assumptions!C$10 | G12: =G4*Assumptions!D$10
A13: Operating income | B13: =Data!B13 | C13: =Data!C13 | D13: =Data!D13 | E13: =E4-E11+E12 | F13: =F4-F11+F12 | G13: =G4-G11+G12
A14: Operating margin | B14: =Data!B14 | C14: =Data!C14 | D14: =Data!D14 | E14: =E13/E4 | F14: =F13/F4 | G14: =G13/G4

Sheet Break-even
A1: Break-even Analysis
A2: Break-even revenue based on contribution margin method
A3: Metric | B3: Formula / Value | C3: Explanation
A4: Revenue 2026E | B4: ='P&L'!E4 | C4: Base forecast revenue
A5: Variable cost ratio 2026E | B5: =Assumptions!B5 | C5: Variable costs as % of revenue
A6: Contribution margin % | B6: =1-B5 | C6: 1 - variable cost ratio
A7: Fixed costs 2026E | B7: ='P&L'!E8+'P&L'!E9+'P&L'!E10 | C7: D&A + G&A + restructuring
A8: Break-even revenue 2026E | B8: =B7/B6 | C8: Fixed costs / contribution margin
A9: Safety margin vs forecast | B9: =B4-B8 | C9: Revenue forecast minus break-even revenue

Sheet Sensitivity
A1: Sensitivity Analysis
A2: 2026E operating income sensitivity to revenue growth and variable cost ratio
A3: Operating income 2026E, USD millions
B4: Variable cost ratio
A5: Revenue growth delta | B5: 0.745 | C5: 0.765 | D5: 0.785
A6: -0.05 | B6: =('P&L'!D4*(1+Assumptions!B4+$A6))*(1-B$5)-('P&L'!E8+'P&L'!E9+Assumptions!B11)+('P&L'!D4*(1+Assumptions!B4+$A6))*Assumptions!B10 | C6: =('P&L'!D4*(1+Assumptions!B4+$A6))*(1-C$5)-('P&L'!E8+'P&L'!E9+Assumptions!B11)+('P&L'!D4*(1+Assumptions!B4+$A6))*Assumptions!B10 | D6: =('P&L'!D4*(1+Assumptions!B4+$A6))*(1-D$5)-('P&L'!E8+'P&L'!E9+Assumptions!B11)+('P&L'!D4*(1+Assumptions!B4+$A6))*Assumptions!B10
A7: 0 | B7: =('P&L'!D4*(1+Assumptions!B4+$A7))*(1-B$5)-('P&L'!E8+'P&L'!E9+Assumptions!B11)+('P&L'!D4*(1+Assumptions!B4+$A7))*Assumptions!B10 | C7: =('P&L'!D4*(1+Assumptions!B4+$A7))*(1-C$5)-('P&L'!E8+'P&L'!E9+Assumptions!B11)+('P&L'!D4*(1+Assumptions!B4+$A7))*Assumptions!B10 | D7: =('P&L'!D4*(1+Assumptions!B4+$A7))*(1-D$5)-('P&L'!E8+'P&L'!E9+Assumptions!B11)+('P&L'!D4*(1+Assumptions!B4+$A7))*Assumptions!B10
A8: 0.05 | B8: =('P&L'!D4*(1+Assumptions!B4+$A8))*(1-B$5)-('P&L'!E8+'P&L'!E9+Assumptions!B11)+('P&L'!D4*(1+Assumptions!B4+$A8))*Assumptions!B10 | C8: =('P&L'!D4*(1+Assumptions!B4+$A8))*(1-C$5)-('P&L'!E8+'P&L'!E9+Assumptions!B11)+('P&L'!D4*(1+Assumptions!B4+$A8))*Assumptions!B10 | D8: =('P&L'!D4*(1+Assumptions!B4+$A8))*(1-D$5)-('P&L'!E8+'P&L'!E9+Assumptions!B11)+('P&L'!D4*(1+Assumptions!B4+$A8))*Assumptions!B10
A11: Interpretation
A12: Higher revenue growth improves operating income, while a higher variable cost ratio quickly compresses profitability.

Sheet Charts
A1: Charts
A2: Revenue, costs, operating income, and margin
A3: Charts are linked to the P&L sheet and update when assumptions change.

Sheet Checks
A1: Model Checks
A2: Basic source, formula, and logic checks
A3: Check | B3: Actual | C3: Expected | D3: Difference | E3: Tolerance | F3: Status
A4: 2025 revenue ties to source | B4: ='P&L'!D4 | C4: =Data!D4 | D4: =B4-C4 | E4: 0.01 | F4: =IF(ABS(D4)<=E4,"OK","Review")
A5: 2025 operating income ties to source formula | B5: ='P&L'!D13 | C5: =Data!D13 | D5: =B5-C5 | E5: 0.01 | F5: =IF(ABS(D5)<=E5,"OK","Review")
A6: 2026 total opex sums components | B6: ='P&L'!E11 | C6: =SUM('P&L'!E5:E10) | D6: =B6-C6 | E6: 0.01 | F6: =IF(ABS(D6)<=E6,"OK","Review")
A7: 2026 operating margin formula | B7: ='P&L'!E14 | C7: ='P&L'!E13/'P&L'!E4 | D7: =B7-C7 | E7: 0.0001 | F7: =IF(ABS(D7)<=E7,"OK","Review")
A8: Break-even safety margin formula | B8: ='Break-even'!B9 | C8: ='Break-even'!B4-'Break-even'!B8 | D8: =B8-C8 | E8: 0.01 | F8: =IF(ABS(D8)<=E8,"OK","Review")
A10: Overall model status | F10: =IF(COUNTIF(F4:F8,"Review")=0,"OK","Review")

Sheet Sources
A1: Sources and Audit Trail
A2: Official Starbucks / SEC source links
A3: Source ID | B3: Source | C3: URL | D3: Notes
A4: S1 | B4: Starbucks Fiscal 2025 Annual Report PDF | C4: https://s203.q4cdn.com/326826266/files/doc_financials/2025/ar/Starbucks-Corporation_2025-Annual-Report-Web-Ready.pdf | D4: Consolidated revenues, operating expenses, operating income, net earnings, segment and business description.
A5: S2 | B5: Starbucks Investor Relations - Annual Reports | C5: https://investor.starbucks.com/financials/annual-reports/ | D5: Official page for Starbucks annual reports.
A6: S3 | B6: Starbucks SEC Filing Details - Form 10-K | C6: https://investor.starbucks.com/financials/sec-filings/sec-filings-details/default.aspx?FilingId=18927461 | D6: Official 10-K filing page dated 2025-11-14 with PDF, Excel, and XBRL downloads.
